LICENSE
setup.py
sentry_telegram_with_proxy/__init__.py
sentry_telegram_with_proxy/plugin.py
sentry_telegram_with_proxy.egg-info/PKG-INFO
sentry_telegram_with_proxy.egg-info/SOURCES.txt
sentry_telegram_with_proxy.egg-info/dependency_links.txt
sentry_telegram_with_proxy.egg-info/entry_points.txt
sentry_telegram_with_proxy.egg-info/top_level.txt