Metadata-Version: 2.1
Name: sentry-telegram-with-proxy
Version: 0.4.1
Summary: Plugin for Sentry which allows sending notification via Telegram messenger.
Home-page: https://github.com/ivantzepner/sentry-telegram
Author: Ivan Tzepner
Author-email: ivan.tzepner@gmail.com
License: MIT
Classifier: Development Status :: 5 - Production/Stable
Classifier: Environment :: Console
Classifier: Intended Audience :: Developers
Classifier: Intended Audience :: System Administrators
Classifier: License :: OSI Approved :: MIT License
Classifier: Operating System :: OS Independent
Classifier: Programming Language :: Python
Classifier: Programming Language :: Python :: 2
Classifier: Programming Language :: Python :: 2.7
Classifier: Programming Language :: Python :: 3
Classifier: Programming Language :: Python :: 3.6
Classifier: Programming Language :: Python :: Implementation :: CPython
Classifier: Topic :: Software Development :: Bug Tracking
Classifier: Topic :: Software Development :: Quality Assurance
Classifier: Topic :: System :: Monitoring
License-File: LICENSE
